[{"name":"d8i0c","marks":61},{"name":"UsoEbIhRAp","marks":54},{"name":"pz","marks":93},{"name":"WBxCeArj","marks":22},{"name":"81fES","marks":37},{"name":"ILdRa","marks":2},{"name":"YO","marks":60},{"name":"MPcKDdbW","marks":46},{"name":"QBVXc5","marks":44},{"name":"6Ye7aR","marks":45},{"name":"s","marks":28},{"name":"Dd","marks":53},{"name":"Cok8n","marks":53},{"name":"49QM","marks":74},{"name":"Y","marks":5},{"name":"VSOBida","marks":39},{"name":"L9","marks":54},{"name":"c5Vu","marks":80},{"name":"7SADeyU","marks":77},{"name":"Hj9Mwgyr0","marks":11},{"name":"0","marks":13},{"name":"BbiVVxqLmN","marks":62},{"name":"9PcXCf","marks":12},{"name":"F","marks":7},{"name":"Q","marks":19},{"name":"VjVFsF4LJ","marks":23},{"name":"iDLYp1bqY","marks":31},{"name":"0tLp","marks":6},{"name":"PMBio0wXxt","marks":33},{"name":"NG3K0bvw","marks":50},{"name":"fcfRvTRbS","marks":56},{"name":"X1I8","marks":66},{"name":"pjx3sAa","marks":96},{"name":"fcbSjYOK","marks":49},{"name":"o3RBT","marks":29},{"name":"uJXGROL","marks":30},{"name":"CVWTFdjJl3","marks":34},{"name":"w92Nbve","marks":27},{"name":"e","marks":28},{"name":"CR","marks":78},{"name":"LFokK","marks":77},{"name":"q","marks":5},{"name":"R0VnG2E","marks":80},{"name":"ATPs7P8ZVh","marks":41},{"name":"Pu","marks":25},{"name":"jw8f0","marks":4},{"name":"eg3","marks":7},{"name":"C4rMgymDO","marks":30},{"name":"H7U","marks":90},{"name":"rFMCaL7","marks":62},{"name":"HR","marks":39},{"name":"GIVzvvBp","marks":2},{"name":"9d2mw9C2","marks":39},{"name":"2qf4qBDoDW","marks":9},{"name":"I","marks":49},{"name":"KGeYVzM","marks":36},{"name":"R","marks":10},{"name":"2","marks":76},{"name":"6JU","marks":60},{"name":"WwVNk31p","marks":64},{"name":"hv6dyjLY","marks":32},{"name":"KhUXeRoh","marks":70},{"name":"F1","marks":63},{"name":"CKGFeAIFU","marks":3},{"name":"X","marks":27},{"name":"u","marks":16},{"name":"u3Qdq2e","marks":30},{"name":"zT3pQZaV","marks":4},{"name":"wVEXi","marks":64},{"name":"Rfgu","marks":55},{"name":"R5rReIGS","marks":49},{"name":"8SB0sFeFbQ","marks":26},{"name":"6lXmrd","marks":61},{"name":"jfAHEf","marks":13},{"name":"uSeH","marks":24},{"name":"acg","marks":46},{"name":"uyJmIpkCFn","marks":64},{"name":"K2s","marks":16},{"name":"gyqSH6","marks":52},{"name":"vlSqA","marks":35},{"name":"5YHO5sjN1Q","marks":86},{"name":"S6poL19","marks":98},{"name":"K","marks":36},{"name":"kPn3caRPIc","marks":32},{"name":"tVGsf5LBz","marks":6},{"name":"v1","marks":70},{"name":"44NUJAT","marks":44},{"name":"5AgWpBOahg","marks":43},{"name":"RliwLI","marks":6},{"name":"VRK0","marks":75},{"name":"5zowK","marks":82},{"name":"wzasayHCv","marks":69},{"name":"S8dZcGW","marks":40},{"name":"vxsZF3SSYp","marks":19},{"name":"uN49ID","marks":50},{"name":"PWvfCSkm","marks":42},{"name":"aJmHpB","marks":11},{"name":"magu","marks":75},{"name":"MirxVIynz","marks":47},{"name":"x","marks":21}]